CircuitPy/AnalogDiscovery.py
CircuitPy/BaseFunction.py
CircuitPy/Test_.py
CircuitPy/__init__.py
Ciruitpy-0.0.1.dist-info/METADATA
Ciruitpy-0.0.1.dist-info/RECORD
Ciruitpy-0.0.1.dist-info/WHEEL
Ciruitpy-0.0.1.dist-info/top_level.txt
